mmr/__init__.py
mmr/mmr.py
tests/__init__.py
tests/test_mmr.py
mmr.py-0.0.4.dist-info/METADATA
mmr.py-0.0.4.dist-info/WHEEL
mmr.py-0.0.4.dist-info/top_level.txt
mmr.py-0.0.4.dist-info/RECORD
