Metadata-Version: 2.1
Name: mmr.py
Version: 0.0.4
Summary: Merkle Mountain Range in python
Home-page: https://github.com/jjyr/mmr.py
Author: jjy
Author-email: jjyruby@gmail.com
License: UNKNOWN
Platform: UNKNOWN
Classifier: Programming Language :: Python :: 3
Classifier: License :: OSI Approved :: MIT License
